setup.py
wayround_org/socketserver/__init__.py
wayround_org/socketserver/server.py
wayround_org/socketserver/service.py
wayround_org_socketserver.egg-info/PKG-INFO
wayround_org_socketserver.egg-info/SOURCES.txt
wayround_org_socketserver.egg-info/dependency_links.txt
wayround_org_socketserver.egg-info/requires.txt
wayround_org_socketserver.egg-info/top_level.txt