Metadata-Version: 1.1
Name: wayround-org-socketserver
Version: 0.1.3
Summary: socket server realisation
Home-page: https://github.com/AnimusPEXUS/wayround_org_socketserver
Author: Alexey Gorshkov
Author-email: animus@wayround.org
License: UNKNOWN
Platform: UNKNOWN
Classifier: License :: OSI Approved :: GNU General Public License v3 or later (GPLv3+)
